{
	"authHost": "api.ppgfood.com.br",
	"authEndpoint": "broadcasting/auth",
	"clients": [
		{
			"appId": "bcb571a63b8841ce",
			"key": "7375789f1b80e8ce6cc6de011dea05b7"
		}
	],
	"database": "redis",
	"databaseConfig": {
		"redis": {},
		"sqlite": {
			"databasePath": "/database/laravel-echo-server.sqlite"
		}
	},
	"devMode": true,
	"host": null,
	"port": "6001",
	"protocol": "https",
	"socketio": {},
	"secureOptions": 67108864,
	"sslCertPath": "/etc/letsencrypt/live/www.ppgfood.com.br/fullchain.pem",

	"sslKeyPath": " /etc/letsencrypt/live/www.ppgfood.com.br/privkey.pem",
	"sslCertChainPath": "",
	"sslPassphrase": "",
	"subscribers": {
		"http": true,
		"redis": true
	},
	"apiOriginAllow": {
		"allowCors": true,
		"allowOrigin": "api.ppgfood.com.br",
		"allowMethods": "GET, POST",
		"allowHeaders": "Origin, Content-Type, X-Auth-Token, X-Requested-With, Accept, Authorization, X-CSRF-TOKEN, X-Socket-Id"
	}
}
